odoo10_addon_l10n_it_fatturapa_in_rc-10.0.2.1.0-py3.8-nspkg.pth
odoo/addons/l10n_it_fatturapa_in_rc/README.rst
odoo/addons/l10n_it_fatturapa_in_rc/__init__.py
odoo/addons/l10n_it_fatturapa_in_rc/__manifest__.py
odoo/addons/l10n_it_fatturapa_in_rc/i18n/l10n_it_fatturapa_in_rc.pot
odoo/addons/l10n_it_fatturapa_in_rc/models/__init__.py
odoo/addons/l10n_it_fatturapa_in_rc/models/account_invoice.py
odoo/addons/l10n_it_fatturapa_in_rc/models/account_rc_type.py
odoo/addons/l10n_it_fatturapa_in_rc/models/attachment.py
odoo/addons/l10n_it_fatturapa_in_rc/readme/CONFIGURE.rst
odoo/addons/l10n_it_fatturapa_in_rc/readme/CONTRIBUTORS.rst
odoo/addons/l10n_it_fatturapa_in_rc/readme/DESCRIPTION.rst
odoo/addons/l10n_it_fatturapa_in_rc/static/description/icon.png
odoo/addons/l10n_it_fatturapa_in_rc/static/description/index.html
odoo/addons/l10n_it_fatturapa_in_rc/tests/__init__.py
odoo/addons/l10n_it_fatturapa_in_rc/tests/test_fatturapa_in_rc.py
odoo/addons/l10n_it_fatturapa_in_rc/tests/data/IT01234567890_FPR04.xml
odoo/addons/l10n_it_fatturapa_in_rc/views/rc_type_view.xml
odoo/addons/l10n_it_fatturapa_in_rc/wizard/__init__.py
odoo/addons/l10n_it_fatturapa_in_rc/wizard/wizard_import_fatturapa.py
odoo10_addon_l10n_it_fatturapa_in_rc-10.0.2.1.0.dist-info/METADATA
odoo10_addon_l10n_it_fatturapa_in_rc-10.0.2.1.0.dist-info/WHEEL
odoo10_addon_l10n_it_fatturapa_in_rc-10.0.2.1.0.dist-info/namespace_packages.txt
odoo10_addon_l10n_it_fatturapa_in_rc-10.0.2.1.0.dist-info/top_level.txt
odoo10_addon_l10n_it_fatturapa_in_rc-10.0.2.1.0.dist-info/RECORD
